odoo/addons/l10n_ro_siruta/README.rst
odoo/addons/l10n_ro_siruta/__init__.py
odoo/addons/l10n_ro_siruta/__manifest__.py
odoo/addons/l10n_ro_siruta/hooks.py
odoo/addons/l10n_ro_siruta/data/res_country_commune.xml
odoo/addons/l10n_ro_siruta/data/res_country_state.xml
odoo/addons/l10n_ro_siruta/data/res_country_zone.xml
odoo/addons/l10n_ro_siruta/demo/demo_siruta.xml
odoo/addons/l10n_ro_siruta/i18n/l10n_ro_siruta.pot
odoo/addons/l10n_ro_siruta/i18n/ro.po
odoo/addons/l10n_ro_siruta/models/__init__.py
odoo/addons/l10n_ro_siruta/models/l10n_ro_res_country_commune.py
odoo/addons/l10n_ro_siruta/models/l10n_ro_res_country_zone.py
odoo/addons/l10n_ro_siruta/models/res_city.py
odoo/addons/l10n_ro_siruta/models/res_country_state.py
odoo/addons/l10n_ro_siruta/models/res_partner.py
odoo/addons/l10n_ro_siruta/readme/CONTRIBUTORS.rst
odoo/addons/l10n_ro_siruta/readme/DESCRIPTION.rst
odoo/addons/l10n_ro_siruta/readme/INSTALL.rst
odoo/addons/l10n_ro_siruta/readme/USAGE.rst
odoo/addons/l10n_ro_siruta/security/ir.model.access.csv
odoo/addons/l10n_ro_siruta/static/description/icon.png
odoo/addons/l10n_ro_siruta/static/description/index.html
odoo/addons/l10n_ro_siruta/static/src/less/form_view.less
odoo/addons/l10n_ro_siruta/static/src/xml/assets.xml
odoo/addons/l10n_ro_siruta/tests/__init__.py
odoo/addons/l10n_ro_siruta/tests/test_siruta.py
odoo/addons/l10n_ro_siruta/views/l10n_ro_res_country_commune_views.xml
odoo/addons/l10n_ro_siruta/views/l10n_ro_res_country_zone_views.xml
odoo/addons/l10n_ro_siruta/views/partner_view.xml
odoo/addons/l10n_ro_siruta/views/res_city_views.xml
odoo/addons/l10n_ro_siruta/views/res_country_state_views.xml
odoo_addon_l10n_ro_siruta-15.0.2.6.0.dist-info/METADATA
odoo_addon_l10n_ro_siruta-15.0.2.6.0.dist-info/WHEEL
odoo_addon_l10n_ro_siruta-15.0.2.6.0.dist-info/top_level.txt
odoo_addon_l10n_ro_siruta-15.0.2.6.0.dist-info/RECORD
