Metadata-Version: 2.1
Name: odoo-addon-l10n-ro-siruta
Version: 15.0.2.6.0
Summary: Romania - Siruta
Home-page: https://github.com/OCA/l10n-romania
Author: NextERP Romania,Forest and Biomass Romania,Terrabit,Odoo Community Association (OCA)
Author-email: support@odoo-community.org
License: AGPL-3
Platform: UNKNOWN
Classifier: Programming Language :: Python
Classifier: Framework :: Odoo
Classifier: Framework :: Odoo :: 15.0
Classifier: License :: OSI Approved :: GNU Affero General Public License v3
Classifier: Development Status :: 6 - Mature
Requires-Python: >=3.8
Requires-Dist: odoo-addon-l10n-ro-city <15.1dev,>=15.0dev
Requires-Dist: odoo <15.1dev,>=15.0a
